.gitignore
.pre-commit-config.yaml
CMakeLists.txt
LICENSE
README.md
pyproject.toml
setup.py
.github/workflows/pytest_linux.yml
.github/workflows/pytest_windows.yml
.github/workflows/release.yml
cmake/CPM.cmake
notebooks/playground.ipynb
src/CMakeLists.txt
src/cgshop2024_pyutils/CMakeLists.txt
src/cgshop2024_pyutils/__init__.py
src/cgshop2024_pyutils/verify.py
src/cgshop2024_pyutils.egg-info/PKG-INFO
src/cgshop2024_pyutils.egg-info/SOURCES.txt
src/cgshop2024_pyutils.egg-info/dependency_links.txt
src/cgshop2024_pyutils.egg-info/requires.txt
src/cgshop2024_pyutils.egg-info/top_level.txt
src/cgshop2024_pyutils/instance_database/__init__.py
src/cgshop2024_pyutils/instance_database/instance_base_database.py
src/cgshop2024_pyutils/instance_database/instance_database.py
src/cgshop2024_pyutils/instance_database/instance_file_database.py
src/cgshop2024_pyutils/instance_database/instance_zip_database.py
src/cgshop2024_pyutils/io/__init__.py
src/cgshop2024_pyutils/io/read.py
src/cgshop2024_pyutils/knapsack/CMakeLists.txt
src/cgshop2024_pyutils/knapsack/__init__.py
src/cgshop2024_pyutils/knapsack/_bindings.cpp
src/cgshop2024_pyutils/knapsack/cgal_defs.h
src/cgshop2024_pyutils/knapsack/knapsack.h
src/cgshop2024_pyutils/knapsack/quadtree.h
src/cgshop2024_pyutils/visualization/__init__.py
src/cgshop2024_pyutils/visualization/plot.py
src/cgshop2024_pyutils/zip/__init__.py
src/cgshop2024_pyutils/zip/zip_processor.py
src/cgshop2024_pyutils/zip/zip_reader_errors.py
tests/test.ipynb
tests/test_basics.py
tests/assets/test_border.json
tests/assets/test_bounds.json
tests/assets/test_highindex.json
tests/assets/test_multi.json
tests/assets/test_negindex.json
tests/assets/test_outside.json
tests/assets/test_overlap.json
tests/assets/test_same_overlap.json
tests/assets/test_same_used.json