Metadata-Version: 2.1
Name: cgshop2024-pyutils
Version: 1.2.2
Summary: Utilities for verifying solutions of the CG:SHOP 2024 Competition.
Author: Dominik Krupke
License: LICENSE
Requires-Python: >=3.7
License-File: LICENSE
Requires-Dist: matplotlib
Requires-Dist: numpy
Requires-Dist: chardet>=4.0.0
Requires-Dist: networkx>=2.0.0
